aeiou/__init__.py
aeiou/_modidx.py
aeiou/chunk_one_file.py
aeiou/chunkadelic.py
aeiou/core.py
aeiou/datasets.py
aeiou/hpc.py
aeiou/spectrofu.py
aeiou/viz.py
aeiou-0.0.21.dist-info/licenses/LICENSE
aeiou-0.0.21.dist-info/METADATA
aeiou-0.0.21.dist-info/WHEEL
aeiou-0.0.21.dist-info/entry_points.txt
aeiou-0.0.21.dist-info/top_level.txt
aeiou-0.0.21.dist-info/RECORD
