Metadata-Version: 2.4
Name: aeiou
Version: 0.0.21
Summary: audio engineering i/o utils
Home-page: https://github.com/drscotthawley/aeiou/
Author: Scott Hawley
Author-email: scott.hawley@belmont.edu
License: Apache Software License 2.0
Keywords: nbdev
Classifier: Development Status :: 3 - Alpha
Classifier: Intended Audience :: Developers
Classifier: Natural Language :: English
Classifier: Programming Language :: Python :: 3.7
Classifier: Programming Language :: Python :: 3.8
Classifier: Programming Language :: Python :: 3.9
Classifier: Programming Language :: Python :: 3.10
Classifier: License :: OSI Approved :: Apache Software License
Requires-Python: >=3.7
License-File: LICENSE
Requires-Dist: fastcore
Requires-Dist: pandas
Requires-Dist: numpy
Requires-Dist: plotly
Requires-Dist: bokeh
Requires-Dist: holoviews
Requires-Dist: scipy
Requires-Dist: torch
Requires-Dist: torchvision
Requires-Dist: torchaudio
Requires-Dist: wandb
Requires-Dist: matplotlib
Requires-Dist: pillow
Requires-Dist: tqdm
Requires-Dist: einops
Requires-Dist: ipython
Requires-Dist: accelerate
Requires-Dist: webdataset
Requires-Dist: pedalboard
Requires-Dist: umap-learn
Provides-Extra: dev
Requires-Dist: nbformat>=4.2.0; extra == "dev"
Dynamic: author
Dynamic: author-email
Dynamic: classifier
Dynamic: description
Dynamic: description-content-type
Dynamic: home-page
Dynamic: keywords
Dynamic: license
Dynamic: license-file
Dynamic: provides-extra
Dynamic: requires-dist
Dynamic: requires-python
Dynamic: summary
